{
  "fileName": "errors.go",
  "filePath": "x/dex/types/errors.go",
  "url": "https://github.com/duality-labs/duality/types/errors.go",
  "summary": "This code is part of the `duality` project and defines a set of custom error messages for the `x/dex` module, which is likely related to a decentralized exchange implementation. These error messages are used to provide more informative feedback to users when something goes wrong during the execution of the module's functions.\n\nThe code starts by importing the `sdkerrors` package from the Cosmos SDK, which is a popular framework for building blockchain applications. It then defines a series of error messages using the `sdkerrors.Register` function, which takes three arguments: the module name, an error code, and a human-readable error message. The error messages are designed to be descriptive and provide context about the specific issue that occurred.\n\nSome examples of the error messages defined in this code include:\n\n- `ErrInvalidTradingPair`: Indicates that an invalid token pair was provided for a trading operation.\n- `ErrInsufficientShares`: Indicates that a user does not have enough shares of a specific type to perform an operation.\n- `ErrValidTickNotFound`: Indicates that a valid tick (likely a price level) was not found during an operation.\n- `ErrUnbalancedTxArray`: Indicates that the transaction input arrays are not of the same length, which is likely a requirement for certain operations.\n\nThese error messages can be used throughout the `x/dex` module to provide more informative feedback to users when something goes wrong. For example, if a user tries to perform a trade with an invalid token pair, the module could return the `ErrInvalidTradingPair` error to inform the user about the issue.\n\nOverall, this code is responsible for defining a set of custom error messages that can be used by the `x/dex` module to provide better feedback to users when something goes wrong during the execution of its functions.",
  "questions": "1. **Question**: What is the purpose of the `sdkerrors.Register` function and what are the parameters it takes?\n   **Answer**: The `sdkerrors.Register` function is used to register custom error codes with their respective error messages for the `x/dex` module. It takes three parameters: the module name, the error code, and the error message.\n\n2. **Question**: What is the `ModuleName` constant used for in this code?\n   **Answer**: The `ModuleName` constant represents the name of the module (`x/dex`) and is used as a parameter when registering errors with `sdkerrors.Register` to associate the errors with the specific module.\n\n3. **Question**: What is the significance of the `//nolint:all` comment in the code?\n   **Answer**: The `//nolint:all` comment is used to instruct the linter to ignore all linting issues in the following code block. This is typically done when the developer intentionally writes code that may not adhere to standard linting rules but is still considered acceptable for the specific use case."
}