{
  "fileName": "hooks.go",
  "filePath": "x/incentives/types/hooks.go",
  "url": "https://github.com/duality-labs/duality/incentives/types/hooks.go",
  "summary": "The `types` package contains an interface called `IncentiveHooks` and a struct called `MultiIncentiveHooks` that implements this interface. The purpose of this code is to provide a way to combine multiple incentive hooks into a single array and run them in sequence. \n\nThe `IncentiveHooks` interface defines a set of methods that can be implemented by other structs to perform certain actions at specific points in the incentive process. These methods include `AfterCreateGauge`, `AfterAddToGauge`, `AfterStartDistribution`, `AfterFinishDistribution`, `AfterEpochDistribution`, `AfterAddTokensToStake`, `OnTokenStaked`, and `OnTokenUnstaked`. \n\nThe `MultiIncentiveHooks` struct is an array of `IncentiveHooks` that implements all of the methods defined in the `IncentiveHooks` interface. The `NewMultiIncentiveHooks` function takes in multiple `IncentiveHooks` and returns a `MultiIncentiveHooks` array that contains all of them. \n\nEach method in the `MultiIncentiveHooks` struct loops through all of the `IncentiveHooks` in the array and calls the corresponding method on each of them. This allows multiple hooks to be executed in sequence when a specific action occurs in the incentive process. \n\nThis code can be used in the larger project to provide a way to execute multiple incentive hooks in sequence. For example, if there are multiple hooks that need to be executed when a new gauge is created, they can be combined into a `MultiIncentiveHooks` array and passed to the `AfterCreateGauge` method. This will ensure that all of the hooks are executed in the correct order. \n\nHere is an example of how this code might be used:\n\n```\n// create two incentive hooks\nhook1 := MyIncentiveHook1{}\nhook2 := MyIncentiveHook2{}\n\n// combine the hooks into a single array\nmultiHooks := types.NewMultiIncentiveHooks(hook1, hook2)\n\n// execute the AfterCreateGauge method with the multiHooks array\nmultiHooks.AfterCreateGauge(ctx, gaugeID)\n```\n\nIn this example, `MyIncentiveHook1` and `MyIncentiveHook2` are two structs that implement the `IncentiveHooks` interface. They are combined into a `MultiIncentiveHooks` array using the `NewMultiIncentiveHooks` function. The `AfterCreateGauge` method is then called on the `multiHooks` array to execute both hooks in sequence.",
  "questions": "1. What is the purpose of the `IncentiveHooks` interface?\n   - The `IncentiveHooks` interface defines a set of methods that can be implemented by types in the `duality` package to handle various events related to incentives.\n2. What is the purpose of the `MultiIncentiveHooks` type?\n   - The `MultiIncentiveHooks` type is a slice of `IncentiveHooks` types that allows multiple incentive hooks to be combined into a single array and run in sequence.\n3. What is the purpose of the commented out `OnStakeupExtend` method?\n   - It is unclear what the purpose of the `OnStakeupExtend` method is, as it is currently commented out. It may have been used in a previous version of the code or may be intended for future use."
}